README.md
setup.cfg
setup.py
test/test_mysql_save_item.py
test/test_postgres_save_item.py
teyespider/__init__.py
teyespider/cli/__init__.py
teyespider/config/__init__.py
teyespider/constants/__init__.py
teyespider/core/__init__.py
teyespider/core/client.py
teyespider/core/config.py
teyespider/core/log.py
teyespider/core/request.py
teyespider/db/__init__.py
teyespider/db/es.py
teyespider/db/kafka.py
teyespider/db/mongo.py
teyespider/db/sql.py
teyespider/pipelines/__init__.py
teyespider/utils/__init__.py
teyespider/utils/config.py
teyespider/utils/data.py
teyespider/utils/scrapy.py
teyespider_sdk.egg-info/PKG-INFO
teyespider_sdk.egg-info/SOURCES.txt
teyespider_sdk.egg-info/dependency_links.txt
teyespider_sdk.egg-info/entry_points.txt
teyespider_sdk.egg-info/requires.txt
teyespider_sdk.egg-info/top_level.txt