Metadata-Version: 2.1
Name: teyespider-sdk
Version: 0.0.3
Summary: Python SDK  
Home-page: UNKNOWN
Author: 
Author-email: 
License: BSD-3-Clause
Platform: UNKNOWN
Classifier: Programming Language :: Python :: 3
Classifier: License :: OSI Approved :: BSD License
Classifier: Operating System :: OS Independent
